sphinx_ref_graph/__init__.py
sphinx_ref_graph/_version.py
sphinx_ref_graph/static/ref_graph.html
sphinx_ref_graph-1.0.2.dist-info/METADATA
sphinx_ref_graph-1.0.2.dist-info/WHEEL
sphinx_ref_graph-1.0.2.dist-info/licenses/LICENSE
sphinx_ref_graph-1.0.2.dist-info/RECORD
