Metadata-Version: 2.4
Name: sphinx-ref-graph
Version: 1.0.2
Summary: A custom Sphinx extension to generate an internal reference graph in a Sphinx book
Author-email: Dennis den Ouden-van der Horst <d.denouden-vanderhorst@tudelft.nl>
License: MIT License
License-File: LICENSE
Requires-Python: >=3.10
Requires-Dist: sphinx
